Workbook

Sheet Inputs
A1: Financial Model Inputs
A3: Number of units | B3: 12
A4: Average Daily Rate (ADR) — GEL | B4: 150
A5: Occupancy rate | B5: 0.75
A6: Operating expenses (% of gross) | B6: 0.3
A7: Management fee (% of gross) | B7: 0.1
A8: CAPEX (low) — GEL | B8: 385000
A9: CAPEX (high) — GEL | B9: 728000

Sheet Summary
A1: Summary Outputs
A3: Nights per unit per year | B3: 365
A4: Booked nights per unit | B4: =B3*Inputs!B4 -> 0
A5: Revenue per unit (GEL) | B5: =Inputs!B3*B4 -> 0
A6: Total gross revenue (GEL) | B6: =Inputs!B2*B5 -> 0
A8: Operating expenses (GEL) | B8: =Inputs!B5*Inputs!B2*Inputs!B5/Inputs!B3 -> 0
A9: Operating expenses (GEL) — 30% of gross | B9: =B6*Inputs!B5 -> 0
A10: Management fee (GEL) — 10% of gross | B10: =B6*Inputs!B6 -> 0
A12: Net distributable cash (GEL) | B12: =B6-B9-B10 -> 0
A14: CAPEX (low) — GEL | B14: =Inputs!B7 -> 0
A15: CAPEX (high) — GEL | B15: =Inputs!B8 -> 0
A17: Implied annual ROI on CAPEX midpoint | B17: =B12/AVERAGE(B14,B15) -> 0

Sheet MonthlyProjection
A1: Monthly Projection (equalized for demo)
F2: Annual Gross (link) | G2: =Summary!B6 -> 0
A3: Month | B3: Gross Revenue | C3: Operating Expenses | D3: Management Fee | F3: Annual OPEX (link) | G3: =Summary!B9 -> 0
A4: Jan | B4: =G2/12 -> 0 | C4: =G3/12 -> 0 | D4: =G4/12 -> 0 | F4: Annual Mgmt (link) | G4: =Summary!B10 -> 0
A5: Feb | B5: =G2/12 -> 0 | C5: =G3/12 -> 0 | D5: =G4/12 -> 0
A6: Mar | B6: =G2/12 -> 0 | C6: =G3/12 -> 0 | D6: =G4/12 -> 0
A7: Apr | B7: =G2/12 -> 0 | C7: =G3/12 -> 0 | D7: =G4/12 -> 0
A8: May | B8: =G2/12 -> 0 | C8: =G3/12 -> 0 | D8: =G4/12 -> 0
A9: Jun | B9: =G2/12 -> 0 | C9: =G3/12 -> 0 | D9: =G4/12 -> 0
A10: Jul | B10: =G2/12 -> 0 | C10: =G3/12 -> 0 | D10: =G4/12 -> 0
A11: Aug | B11: =G2/12 -> 0 | C11: =G3/12 -> 0 | D11: =G4/12 -> 0
A12: Sep | B12: =G2/12 -> 0 | C12: =G3/12 -> 0 | D12: =G4/12 -> 0
A13: Oct | B13: =G2/12 -> 0 | C13: =G3/12 -> 0 | D13: =G4/12 -> 0
A14: Nov | B14: =G2/12 -> 0 | C14: =G3/12 -> 0 | D14: =G4/12 -> 0
A15: Dec | B15: =G2/12 -> 0 | C15: =G3/12 -> 0 | D15: =G4/12 -> 0
A18: Monthly Net Distributable (per month) | B18: =Summary!B12/12 -> 0

Sheet Sensitivity
A1: Sensitivity: Net Distributable GEL vs ADR/Occupancy
B2: ADR ₾120 | C2: ADR ₾150 | D2: ADR ₾180 | E2: ADR ₾210
A3: Occ 60% | B3: =Inputs!B2*120*365*0.6*(1-Inputs!B5-Inputs!B6) -> 0 | C3: =Inputs!B2*150*365*0.6*(1-Inputs!B5-Inputs!B6) -> 0 | D3: =Inputs!B2*180*365*0.6*(1-Inputs!B5-Inputs!B6) -> 0 | E3: =Inputs!B2*210*365*0.6*(1-Inputs!B5-Inputs!B6) -> 0
A4: Occ 75% | B4: =Inputs!B2*120*365*0.75*(1-Inputs!B5-Inputs!B6) -> 0 | C4: =Inputs!B2*150*365*0.75*(1-Inputs!B5-Inputs!B6) -> 0 | D4: =Inputs!B2*180*365*0.75*(1-Inputs!B5-Inputs!B6) -> 0 | E4: =Inputs!B2*210*365*0.75*(1-Inputs!B5-Inputs!B6) -> 0
A5: Occ 90% | B5: =Inputs!B2*120*365*0.9*(1-Inputs!B5-Inputs!B6) -> 0 | C5: =Inputs!B2*150*365*0.9*(1-Inputs!B5-Inputs!B6) -> 0 | D5: =Inputs!B2*180*365*0.9*(1-Inputs!B5-Inputs!B6) -> 0 | E5: =Inputs!B2*210*365*0.9*(1-Inputs!B5-Inputs!B6) -> 0

Sheet CapTable
A1: Cap Table & Payout Calculator
A3: Ownership % (enter) | B3: Monthly Payout (GEL)
A4: 0.01 | B4: =Summary!B12/12*A4 -> 0
A5: 0.02 | B5: =Summary!B12/12*A5 -> 0
A6: 0.03 | B6: =Summary!B12/12*A6 -> 0
A7: 0.04 | B7: =Summary!B12/12*A7 -> 0
A8: 0.05 | B8: =Summary!B12/12*A8 -> 0
A9: 0.06 | B9: =Summary!B12/12*A9 -> 0
A10: 0.07 | B10: =Summary!B12/12*A10 -> 0
A11: 0.08 | B11: =Summary!B12/12*A11 -> 0
A12: 0.09 | B12: =Summary!B12/12*A12 -> 0
A13: 0.1 | B13: =Summary!B12/12*A13 -> 0
A16: Example: 1% share monthly payout (excerpt) | B16: =Summary!B12/12*1% -> 0
